{
  "_schema": "process_v2",
  "_note": "P-Additive: 3 extra perform steps before buy. execution_order: extra_step_0=extra_step_1=extra_step_2=1, buy_0=2, go_entity=3.",

  "type": "sequence",
  "root": "defeat_0",

  "ordering_constraints": [],

  "steps": [
    {
      "id": "extra_step_0",
      "action": "perform",
      "execution_order": 1,
      "parent": "defeat_0",
      "is_hidden": true,
      "argument": {"pool": "activity.ritual"}
    },
    {
      "id": "extra_step_1",
      "action": "perform",
      "execution_order": 1,
      "parent": "defeat_0",
      "is_hidden": true,
      "argument": {"pool": "activity.ritual"}
    },
    {
      "id": "extra_step_2",
      "action": "perform",
      "execution_order": 1,
      "parent": "defeat_0",
      "is_hidden": true,
      "argument": {"pool": "activity.ritual"}
    },
    {
      "id": "go_item",
      "action": "go",
      "execution_order": 0,
      "parent": "buy_0",
      "argument": {"from": "buy_0.location"}
    },
    {
      "id": "buy_0",
      "action": "buy",
      "execution_order": 2,
      "parent": "defeat_0",
      "argument": {"pool": "object.weapon"}
    },
    {
      "id": "go_entity",
      "action": "go",
      "execution_order": 3,
      "parent": "defeat_0",
      "argument": {"from": "defeat_0.location"}
    },
    {
      "id": "defeat_0",
      "action": "defeat",
      "argument": {"pool": "entity.npc"}
    }
  ]
}
